{".pdf":{"D:\\qqfile\\1397645429\\FileRecv\\C语言程序设计\\习题答案":["2习题二-参考答案.pdf","3习题三-参考答案.pdf","4习题四-参考答案.pdf","5习题五-参考答案.pdf","6习题六-参考答案.pdf","7习题七-参考答案.pdf"],"D:\\qqfile\\1397645429\\FileRecv":["电路理论基础第六章答案.pdf"]},".txt":{"D:\\qqfile\\1397645429\\FileRecv":["Analyze.txt","analyzer.txt"]},".doc":{"D:\\qqfile\\1397645429\\FileRecv":["2005秋试题.doc","2006秋试题.doc","2007秋试题.doc","2008秋试题.doc","2014_A) (1).doc","2014_A)-answer.doc","2014级2015春阶段测试参考题型.doc","2015年夏季学期本科生课程预选通知.doc","2015年春季学期（工数机考）.doc","2015年春班助联系簿.doc","2015年秋季学期本科生课程预选通知.doc","2015春大学英语期末考试安排(第17周周日10：00-12：00) (1).doc","2015春大学英语期末考试安排(第17周周日10：00-12：00).doc","2015春季期中成绩分析.doc","个人数字图书馆中期检查报告.doc"],"D:\\qqfile\\1397645429\\FileRecv\\2014级2015秋拓展课介绍":["学术英语写作简介 .doc","实用英文写作简介.doc","翻译实践简介.doc","英语文化基础简介.doc","英语视听说简介.doc","英语词汇提高简介.doc","英语阅读进阶简介.doc","走进北美文化简介.doc"]}}